README.rst
setup.py
geextract/__init__.py
geextract.egg-info/PKG-INFO
geextract.egg-info/SOURCES.txt
geextract.egg-info/dependency_links.txt
geextract.egg-info/requires.txt
geextract.egg-info/top_level.txt
geextract/scripts/gee_extract.py
geextract/scripts/gee_extract_batch.py
tests/__init__.py
tests/test_db.py
tests/test_extract.py
tests/test_utils.py