Metadata-Version: 2.1
Name: geextract
Version: 0.5.0
Summary: Extract Landsat surface reflectance time-series at given location from google earth engine
Home-page: https://github.com/loicdtx/landsat-extract-gee.git
Author: Loïc Dutrieux
Author-email: loic.dutrieux@gmail.com
License: GPLv3
Keywords: Landsat,surface reflectance,google,gee,time-series
Platform: UNKNOWN
Provides-Extra: all
Provides-Extra: docs
